iagon/__init__.py
iagon/base.py
iagon/fs.py
iagon_py-0.1.1.dist-info/entry_points.txt
iagon_py-0.1.1.dist-info/LICENSE
iagon_py-0.1.1.dist-info/METADATA
iagon_py-0.1.1.dist-info/WHEEL
iagon_py-0.1.1.dist-info/RECORD
