Metadata-Version: 2.1
Name: iagon-py
Version: 0.1.1
Summary: A Python client for Iagon's decentralized cloud storage platform.
Home-page: https://github.com/theeldermillenial/iagon-py
Author: Elder Millenial
Author-email: eldermillenial@protonmail.com
Requires-Python: >=3.10,<4.0
Classifier: Programming Language :: Python :: 3
Classifier: Programming Language :: Python :: 3.10
Classifier: Programming Language :: Python :: 3.11
Requires-Dist: fsspec (>=2023.9.0,<2024.0.0)
Requires-Dist: pycardano (>=0.10.0,<0.11.0)
Requires-Dist: pydantic (>=2.3.0,<3.0.0)
Requires-Dist: python-dotenv (>=1.0.0,<2.0.0)
Requires-Dist: requests (>=2.31.0,<3.0.0)
Project-URL: Repository, https://github.com/theeldermillenial/iagon-py
